reportcard/__init__.py
reportcard/reportcard.py
reportcard-0.1.dist-info/LICENSE
reportcard-0.1.dist-info/METADATA
reportcard-0.1.dist-info/WHEEL
reportcard-0.1.dist-info/top_level.txt
reportcard-0.1.dist-info/RECORD
